easyass/__init__.py
easyass/__version__.py
easyass/easyass.py
easyass/common/__init__.py
easyass/common/assattr.py
easyass/common/asstypes.py
easyass/common/errors.py
easyass/events/__init__.py
easyass/events/events.py
easyass/events/text.py
easyass/scriptinfo/__init__.py
easyass/scriptinfo/scriptinfo.py
easyass/styles/__init__.py
easyass/styles/styles.py
easyass-1.0.0b12.dist-info/LICENSE
easyass-1.0.0b12.dist-info/METADATA
easyass-1.0.0b12.dist-info/WHEEL
easyass-1.0.0b12.dist-info/top_level.txt
easyass-1.0.0b12.dist-info/RECORD
