Metadata-Version: 2.1
Name: easyass
Version: 1.0.0b12
Summary: An ass subtitle parsing library
Home-page: https://github.com/hihkm/easyAss
Author: tikm
Author-email: hkm@tikm.org
License: MIT Licence
Keywords: ass,subtitle
Platform: all
Classifier: Programming Language :: Python :: 3
Classifier: License :: OSI Approved :: MIT License
Classifier: Operating System :: OS Independent
Requires-Python: >=3.7
License-File: LICENSE
